Metadata-Version: 1.0
Name: django-vouchers
Version: 0.5
Summary: Vouchers in Django
Home-page: https://github.com/yeago/django-vouchers
Author: Federico Castro
Author-email: fmc0208@gmail.com
License: UNKNOWN
Platform: UNKNOWN
Classifier: Framework :: Django
Classifier: Intended Audience :: Developers
Classifier: Intended Audience :: System Administrators
Classifier: Operating System :: OS Independent
Classifier: Topic :: Software Development
